LICENSE
MANIFEST.in
README.md
setup.py
tests/__init__.py
tests/http_response_catcher.py
tests/test_helper.py
tests/controllers/__init__.py
tests/controllers/controller_test_base.py
tests/controllers/test_api_controller.py
uwygtfvjha/__init__.py
uwygtfvjha/api_helper.py
uwygtfvjha/configuration.py
uwygtfvjha/decorators.py
uwygtfvjha/uwygtfvjha_client.py
uwygtfvjha.egg-info/PKG-INFO
uwygtfvjha.egg-info/SOURCES.txt
uwygtfvjha.egg-info/dependency_links.txt
uwygtfvjha.egg-info/requires.txt
uwygtfvjha.egg-info/top_level.txt
uwygtfvjha/controllers/__init__.py
uwygtfvjha/controllers/api_controller.py
uwygtfvjha/controllers/base_controller.py
uwygtfvjha/exceptions/__init__.py
uwygtfvjha/exceptions/api_exception.py
uwygtfvjha/http/__init__.py
uwygtfvjha/http/http_call_back.py
uwygtfvjha/http/http_client.py
uwygtfvjha/http/http_context.py
uwygtfvjha/http/http_method_enum.py
uwygtfvjha/http/http_request.py
uwygtfvjha/http/http_response.py
uwygtfvjha/http/requests_client.py
uwygtfvjha/http/auth/__init__.py
uwygtfvjha/http/auth/basic_auth.py
uwygtfvjha/models/__init__.py
uwygtfvjha/models/suite_code_enum.py